{"info":{"_postman_id":"061b9d06-dabc-4d9b-98e0-702aeaf5e8ab","name":"trading-springboot-project","schema":"https://schema.getpostman.com/json/collection/v2.1.0/collection.json"},"item":[{"name":"http://localhost:8000/api/categories","id":"959950ea-3658-4d5d-97f0-cb6f45a99282","protocolProfileBehavior":{"disableBodyPruning":true},"request":{"method":"POST","header":[],"body":{"mode":"urlencoded","urlencoded":[{"key":"name","value":"","type":"text"}]},"url":{"raw":"http://localhost:8000/api/categories","protocol":"http","host":["localhost"],"port":"8000","path":["api","categories"]}},"response":[]}]}